ctxwait/__init__.py
ctxwait/constants.py
ctxwait/timeoutcontext.py
ctxwait/waiting.py
contextualwaiting-1.0.2.dist-info/WHEEL
contextualwaiting-1.0.2.dist-info/LICENSE.txt
contextualwaiting-1.0.2.dist-info/METADATA
contextualwaiting-1.0.2.dist-info/RECORD
